JiagoushiZhiLu58Shenjian/README.md
JiagoushiZhiLu58Shenjian/__init__.py
JiagoushiZhiLu58Shenjian/__main__.py
JiagoushiZhiLu58Shenjian/file.epub
JiagoushiZhiLu58Shenjian/index.html
JiagoushiZhiLu58Shenjian/css/__init__.py
JiagoushiZhiLu58Shenjian/css/annotations.css
JiagoushiZhiLu58Shenjian/css/main.css
JiagoushiZhiLu58Shenjian/css/normalize.css
JiagoushiZhiLu58Shenjian/css/popup.css
JiagoushiZhiLu58Shenjian/font/__init__.py
JiagoushiZhiLu58Shenjian/font/fontello.eot
JiagoushiZhiLu58Shenjian/font/fontello.svg
JiagoushiZhiLu58Shenjian/font/fontello.ttf
JiagoushiZhiLu58Shenjian/font/fontello.woff
JiagoushiZhiLu58Shenjian/img/__init__.py
JiagoushiZhiLu58Shenjian/img/annotator-glyph-sprite.png
JiagoushiZhiLu58Shenjian/img/annotator-icon-sprite.png
JiagoushiZhiLu58Shenjian/img/apple-touch-icon.png
JiagoushiZhiLu58Shenjian/img/cancelfullscreen.png
JiagoushiZhiLu58Shenjian/img/close.png
JiagoushiZhiLu58Shenjian/img/fullscreen.png
JiagoushiZhiLu58Shenjian/img/loader.gif
JiagoushiZhiLu58Shenjian/img/menu-icon.png
JiagoushiZhiLu58Shenjian/img/save.png
JiagoushiZhiLu58Shenjian/img/saved.png
JiagoushiZhiLu58Shenjian/img/settings-s.png
JiagoushiZhiLu58Shenjian/img/settings.png
JiagoushiZhiLu58Shenjian/img/star.png
JiagoushiZhiLu58Shenjian/js/__init__.py
JiagoushiZhiLu58Shenjian/js/epub.js
JiagoushiZhiLu58Shenjian/js/epub.min.js
JiagoushiZhiLu58Shenjian/js/epub.min.map
JiagoushiZhiLu58Shenjian/js/hooks.min.js
JiagoushiZhiLu58Shenjian/js/hooks.min.map
JiagoushiZhiLu58Shenjian/js/reader.js
JiagoushiZhiLu58Shenjian/js/reader.js.map
JiagoushiZhiLu58Shenjian/js/reader.min.js
JiagoushiZhiLu58Shenjian/js/reader.min.map
JiagoushiZhiLu58Shenjian/js/hooks/__init__.py
JiagoushiZhiLu58Shenjian/js/hooks/extensions/__init__.py
JiagoushiZhiLu58Shenjian/js/hooks/extensions/highlight.js
JiagoushiZhiLu58Shenjian/js/libs/__init__.py
JiagoushiZhiLu58Shenjian/js/libs/jquery.min.js
JiagoushiZhiLu58Shenjian/js/libs/localforage.min.js
JiagoushiZhiLu58Shenjian/js/libs/screenfull.js
jiagoushi_zhi_lu_58_shenjian-2024.3.2.0.dist-info/METADATA
jiagoushi_zhi_lu_58_shenjian-2024.3.2.0.dist-info/WHEEL
jiagoushi_zhi_lu_58_shenjian-2024.3.2.0.dist-info/entry_points.txt
jiagoushi_zhi_lu_58_shenjian-2024.3.2.0.dist-info/top_level.txt
jiagoushi_zhi_lu_58_shenjian-2024.3.2.0.dist-info/RECORD
